cloudshell/__init__.py
cloudshell/rest/__init__.py
cloudshell/rest/api.py
cloudshell/rest/exceptions.py
cloudshell/rest/models.py
cloudshell/rest/progress_bar.py
tests/__init__.py
tests/multipart_matcher.py
tests/test_api.py
cloudshell_rest_api-9.0.0.dist-info/AUTHORS.rst
cloudshell_rest_api-9.0.0.dist-info/LICENSE
cloudshell_rest_api-9.0.0.dist-info/METADATA
cloudshell_rest_api-9.0.0.dist-info/WHEEL
cloudshell_rest_api-9.0.0.dist-info/top_level.txt
cloudshell_rest_api-9.0.0.dist-info/RECORD
