Metadata-Version: 2.1
Name: cloudshell-rest-api
Version: 9.0.0
Summary: Python client for the CloudShell REST API
Home-page: https://github.com/QualiSystems/cloudshell-rest-api
Author: Boris Modylevsky
Author-email: borismod@gmail.com
License: Apache Software License 2.0
Keywords: cloudshell quali sandbox cloud rest api
Classifier: Development Status :: 5 - Production/Stable
Classifier: Intended Audience :: Developers
Classifier: License :: OSI Approved :: Apache Software License
Classifier: Natural Language :: English
Classifier: Programming Language :: Python :: 3.7
Classifier: Programming Language :: Python :: 3.9
Requires-Python: ~=3.7
License-File: LICENSE
License-File: AUTHORS.rst
Requires-Dist: requests (<3,>=2.23)
Requires-Dist: attrs (<24,>=21)
Requires-Dist: typing-extensions (>=4.4)
Requires-Dist: alive-progress (~=3.0)
Requires-Dist: requests-toolbelt (~=1.0)
